<?xml version="1.0" encoding="utf-8" ?>
<widget id="com.mendix.finch.widget.navlink.NavLink" pluginWidget="true" offlineCapable="false" xmlns="http://www.mendix.com/widget/1.0/" xmlns:xsi="http://www.w3.org/2001/XMLSchema-instance" xsi:schemaLocation="http://www.mendix.com/widget/1.0/ ../node_modules/mendix/custom_widget.xsd">
    <name>NavLink</name>
    <description>Navigation link</description>
    <studioProCategory>Finch</studioProCategory>
    <studioCategory />
    <helpUrl />
    <properties>
        <propertyGroup caption="General">
            <property key="label" type="string" required="false">
                <caption>Label</caption>
                <description>Main link label</description>
            </property>
            <property key="active" type="boolean" required="true" defaultValue="false">
                <caption>Active</caption>
                <description>Determines whether the link should have active styles</description>
            </property>
        </propertyGroup>
    </properties>
</widget>
